oso_cloud/__init__.py
oso_cloud/api.py
oso_cloud/for_agents.py
oso_cloud/helpers.py
oso_cloud/oso.py
oso_cloud/parity_handle.py
oso_cloud/py.typed
oso_cloud/query.py
oso_cloud/types.py
oso_cloud/version.py
oso_cloud-2.5.1.dist-info/METADATA
oso_cloud-2.5.1.dist-info/WHEEL
oso_cloud-2.5.1.dist-info/top_level.txt
oso_cloud-2.5.1.dist-info/RECORD
