Metadata-Version: 2.1
Name: oso-cloud
Version: 2.5.1
Summary: Oso Cloud Python client
Home-page: https://www.osohq.com
Author: Oso Security
Author-email: support@osohq.com
License: Apache-2.0
Project-URL: Documentation, https://www.osohq.com/docs
Keywords: authorization,rbac,oso,oso cloud,authorization as a service,microservice authorization
Classifier: Development Status :: 5 - Production/Stable
Classifier: Intended Audience :: Developers
Classifier: Operating System :: Unix
Classifier: Operating System :: POSIX
Classifier: Operating System :: Microsoft :: Windows
Classifier: Programming Language :: Python
Classifier: Programming Language :: Python :: 3.6
Classifier: Programming Language :: Python :: 3.7
Classifier: Programming Language :: Python :: 3.8
Classifier: Programming Language :: Python :: 3.9
Classifier: Programming Language :: Python :: 3.10
Classifier: Programming Language :: Python :: 3.11
Classifier: Programming Language :: Python :: Implementation :: CPython
Classifier: Programming Language :: Python :: Implementation :: PyPy
Requires-Python: >=3.8
Requires-Dist: requests>=2.27.1
Requires-Dist: backoff>=2.0.0
Requires-Dist: typing-extensions>=4.12.2
